RequestsStampede/__init__.py
RequestsStampede/config.py
RequestsStampede/exceptions.py
RequestsStampede/horde.py
RequestsStampede/models.py
RequestsStampede/policy/__init__.py
RequestsStampede/policy/backoff.py
RequestsStampede/policy/retry.py
RequestsStampede-0.9.1.dist-info/LICENSE
RequestsStampede-0.9.1.dist-info/METADATA
RequestsStampede-0.9.1.dist-info/WHEEL
RequestsStampede-0.9.1.dist-info/top_level.txt
RequestsStampede-0.9.1.dist-info/RECORD
