Metadata-Version: 2.1
Name: RequestsStampede
Version: 0.9.1
Summary: A wrapper around the Requests library that provides request retry logic and backoff delays.
Home-page: https://github.com/patrickmurray/RequestsStampede
Author: Patrick Murray
Author-email: patrick@murray.systems
License: MIT
Platform: UNKNOWN
Classifier: License :: OSI Approved :: MIT License
Classifier: Intended Audience :: Developers
Classifier: Programming Language :: Python
Classifier: Programming Language :: Python :: 3
Classifier: Programming Language :: Python :: 3.6
Classifier: Programming Language :: Python :: 3.7
Classifier: Programming Language :: Python :: 3.8
Classifier: Programming Language :: Python :: 3.9
Classifier: Topic :: Software Development
Classifier: Operating System :: POSIX
Classifier: Operating System :: Unix
Classifier: Operating System :: MacOS
Requires-Python: >=3.7
Requires-Dist: schema (>=0.7.4)
Requires-Dist: pyyaml (>=5.4.1)
Requires-Dist: requests (>=2.25.1)
